pyoverlay/__init__.py
pyoverlay/helper.py
pyoverlay/overlay.py
pyoverlay-1.0.4.dist-info/LICENSE
pyoverlay-1.0.4.dist-info/METADATA
pyoverlay-1.0.4.dist-info/WHEEL
pyoverlay-1.0.4.dist-info/top_level.txt
pyoverlay-1.0.4.dist-info/RECORD
