Metadata-Version: 2.1
Name: pyoverlay
Version: 1.0.4
Summary: Easily create overlay on top of any game/application
Author-email: majvax <majvax.contact@gmail.com>
Project-URL: Homepage, https://github.com/majvax/pyoverlay
Project-URL: Bug Tracker, https://github.com/majvax/pyoverlay/issues
Classifier: Programming Language :: Python :: 3
Classifier: License :: OSI Approved :: MIT License
Classifier: Operating System :: Microsoft :: Windows
Requires-Python: >=3.9
License-File: LICENSE
Requires-Dist: pywin32
Requires-Dist: PyOpenGL ==3.1.6
Requires-Dist: PyOpenGL-accelerate ==3.1.6
Requires-Dist: glfw
